{
  "relationships_close_friends": [
    {
      "title": "",
      "media_list_data": [
        
      ],
      "string_list_data": [
        {
          "href": "https://www.instagram.com/vicherself",
          "value": "vicherself",
          "timestamp": 1773955035
        }
      ]
    },
    {
      "title": "",
      "media_list_data": [
        
      ],
      "string_list_data": [
        {
          "href": "https://www.instagram.com/alex_hanisch",
          "value": "alex_hanisch",
          "timestamp": 1773954919
        }
      ]
    },
    {
      "title": "",
      "media_list_data": [
        
      ],
      "string_list_data": [
        {
          "href": "https://www.instagram.com/tj.trstr_",
          "value": "tj.trstr_",
          "timestamp": 1773520337
        }
      ]
    },
    {
      "title": "",
      "media_list_data": [
        
      ],
      "string_list_data": [
        {
          "href": "https://www.instagram.com/tinojtroester",
          "value": "tinojtroester",
          "timestamp": 1773520317
        }
      ]
    },
    {
      "title": "",
      "media_list_data": [
        
      ],
      "string_list_data": [
        {
          "href": "https://www.instagram.com/avvnyya",
          "value": "avvnyya",
          "timestamp": 1767037396
        }
      ]
    },
    {
      "title": "",
      "media_list_data": [
        
      ],
      "string_list_data": [
        {
          "href": "https://www.instagram.com/fbrice.r",
          "value": "fbrice.r",
          "timestamp": 1767037394
        }
      ]
    },
    {
      "title": "",
      "media_list_data": [
        
      ],
      "string_list_data": [
        {
          "href": "https://www.instagram.com/carsten_atk",
          "value": "carsten_atk",
          "timestamp": 1767037383
        }
      ]
    },
    {
      "title": "",
      "media_list_data": [
        
      ],
      "string_list_data": [
        {
          "href": "https://www.instagram.com/bbymix._",
          "value": "bbymix._",
          "timestamp": 1767037354
        }
      ]
    },
    {
      "title": "",
      "media_list_data": [
        
      ],
      "string_list_data": [
        {
          "href": "https://www.instagram.com/alisxlis",
          "value": "alisxlis",
          "timestamp": 1767037348
        }
      ]
    },
    {
      "title": "",
      "media_list_data": [
        
      ],
      "string_list_data": [
        {
          "href": "https://www.instagram.com/clara_lzc",
          "value": "clara_lzc",
          "timestamp": 1767037338
        }
      ]
    },
    {
      "title": "",
      "media_list_data": [
        
      ],
      "string_list_data": [
        {
          "href": "https://www.instagram.com/chris.instinct",
          "value": "chris.instinct",
          "timestamp": 1767037322
        }
      ]
    },
    {
      "title": "",
      "media_list_data": [
        
      ],
      "string_list_data": [
        {
          "href": "https://www.instagram.com/nielsvermeiree",
          "value": "nielsvermeiree",
          "timestamp": 1767037307
        }
      ]
    },
    {
      "title": "",
      "media_list_data": [
        
      ],
      "string_list_data": [
        {
          "href": "https://www.instagram.com/kjerm_a",
          "value": "kjerm_a",
          "timestamp": 1767037297
        }
      ]
    },
    {
      "title": "",
      "media_list_data": [
        
      ],
      "string_list_data": [
        {
          "href": "https://www.instagram.com/tils303",
          "value": "tils303",
          "timestamp": 1767037289
        }
      ]
    },
    {
      "title": "",
      "media_list_data": [
        
      ],
      "string_list_data": [
        {
          "href": "https://www.instagram.com/dj.dreimal.t",
          "value": "dj.dreimal.t",
          "timestamp": 1767037276
        }
      ]
    },
    {
      "title": "",
      "media_list_data": [
        
      ],
      "string_list_data": [
        {
          "href": "https://www.instagram.com/laracellini",
          "value": "laracellini",
          "timestamp": 1756460959
        }
      ]
    },
    {
      "title": "",
      "media_list_data": [
        
      ],
      "string_list_data": [
        {
          "href": "https://www.instagram.com/efiicore",
          "value": "efiicore",
          "timestamp": 1753432167
        }
      ]
    },
    {
      "title": "",
      "media_list_data": [
        
      ],
      "string_list_data": [
        {
          "href": "https://www.instagram.com/schefxd",
          "value": "schefxd",
          "timestamp": 1753432159
        }
      ]
    },
    {
      "title": "",
      "media_list_data": [
        
      ],
      "string_list_data": [
        {
          "href": "https://www.instagram.com/lindenbergsupport",
          "value": "lindenbergsupport",
          "timestamp": 1742840349
        }
      ]
    },
    {
      "title": "",
      "media_list_data": [
        
      ],
      "string_list_data": [
        {
          "href": "https://www.instagram.com/moritz_werner",
          "value": "moritz_werner",
          "timestamp": 1740299754
        }
      ]
    },
    {
      "title": "",
      "media_list_data": [
        
      ],
      "string_list_data": [
        {
          "href": "https://www.instagram.com/weck__paul__",
          "value": "weck__paul__",
          "timestamp": 1740299746
        }
      ]
    },
    {
      "title": "",
      "media_list_data": [
        
      ],
      "string_list_data": [
        {
          "href": "https://www.instagram.com/_nder__",
          "value": "_nder__",
          "timestamp": 1740299509
        }
      ]
    },
    {
      "title": "",
      "media_list_data": [
        
      ],
      "string_list_data": [
        {
          "href": "https://www.instagram.com/gisura.ve",
          "value": "gisura.ve",
          "timestamp": 1740299473
        }
      ]
    },
    {
      "title": "",
      "media_list_data": [
        
      ],
      "string_list_data": [
        {
          "href": "https://www.instagram.com/cavan.uf",
          "value": "cavan.uf",
          "timestamp": 1740299402
        }
      ]
    },
    {
      "title": "",
      "media_list_data": [
        
      ],
      "string_list_data": [
        {
          "href": "https://www.instagram.com/invexis_live",
          "value": "invexis_live",
          "timestamp": 1740299379
        }
      ]
    },
    {
      "title": "",
      "media_list_data": [
        
      ],
      "string_list_data": [
        {
          "href": "https://www.instagram.com/no7ion",
          "value": "no7ion",
          "timestamp": 1740275139
        }
      ]
    },
    {
      "title": "",
      "media_list_data": [
        
      ],
      "string_list_data": [
        {
          "href": "https://www.instagram.com/florian_boerde_tr4r_charmin",
          "value": "florian_boerde_tr4r_charmin",
          "timestamp": 1738150835
        }
      ]
    },
    {
      "title": "",
      "media_list_data": [
        
      ],
      "string_list_data": [
        {
          "href": "https://www.instagram.com/adrianreich.ardt",
          "value": "adrianreich.ardt",
          "timestamp": 1738150575
        }
      ]
    },
    {
      "title": "",
      "media_list_data": [
        
      ],
      "string_list_data": [
        {
          "href": "https://www.instagram.com/flawlessissues777",
          "value": "flawlessissues777",
          "timestamp": 1738150550
        }
      ]
    },
    {
      "title": "",
      "media_list_data": [
        
      ],
      "string_list_data": [
        {
          "href": "https://www.instagram.com/lasl0.o",
          "value": "lasl0.o",
          "timestamp": 1738093496
        }
      ]
    },
    {
      "title": "",
      "media_list_data": [
        
      ],
      "string_list_data": [
        {
          "href": "https://www.instagram.com/scriptor909",
          "value": "scriptor909",
          "timestamp": 1737416570
        }
      ]
    },
    {
      "title": "",
      "media_list_data": [
        
      ],
      "string_list_data": [
        {
          "href": "https://www.instagram.com/cravo_hayes",
          "value": "cravo_hayes",
          "timestamp": 1735669175
        }
      ]
    },
    {
      "title": "",
      "media_list_data": [
        
      ],
      "string_list_data": [
        {
          "href": "https://www.instagram.com/sonic4j",
          "value": "sonic4j",
          "timestamp": 1735669147
        }
      ]
    },
    {
      "title": "",
      "media_list_data": [
        
      ],
      "string_list_data": [
        {
          "href": "https://www.instagram.com/lenjabrt",
          "value": "lenjabrt",
          "timestamp": 1735669092
        }
      ]
    },
    {
      "title": "",
      "media_list_data": [
        
      ],
      "string_list_data": [
        {
          "href": "https://www.instagram.com/love.lenja",
          "value": "love.lenja",
          "timestamp": 1735669091
        }
      ]
    },
    {
      "title": "",
      "media_list_data": [
        
      ],
      "string_list_data": [
        {
          "href": "https://www.instagram.com/saraminabe",
          "value": "saraminabe",
          "timestamp": 1734942374
        }
      ]
    },
    {
      "title": "",
      "media_list_data": [
        
      ],
      "string_list_data": [
        {
          "href": "https://www.instagram.com/semo.wav",
          "value": "semo.wav",
          "timestamp": 1734942305
        }
      ]
    },
    {
      "title": "",
      "media_list_data": [
        
      ],
      "string_list_data": [
        {
          "href": "https://www.instagram.com/manjahabdank",
          "value": "manjahabdank",
          "timestamp": 1734942297
        }
      ]
    },
    {
      "title": "",
      "media_list_data": [
        
      ],
      "string_list_data": [
        {
          "href": "https://www.instagram.com/valentintaylorgerlmayer",
          "value": "valentintaylorgerlmayer",
          "timestamp": 1734942276
        }
      ]
    },
    {
      "title": "",
      "media_list_data": [
        
      ],
      "string_list_data": [
        {
          "href": "https://www.instagram.com/handfeuergiraphael",
          "value": "handfeuergiraphael",
          "timestamp": 1727352959
        }
      ]
    },
    {
      "title": "",
      "media_list_data": [
        
      ],
      "string_list_data": [
        {
          "href": "https://www.instagram.com/noescapemika",
          "value": "noescapemika",
          "timestamp": 1727214836
        }
      ]
    },
    {
      "title": "",
      "media_list_data": [
        
      ],
      "string_list_data": [
        {
          "href": "https://www.instagram.com/maikhelm.nkr",
          "value": "maikhelm.nkr",
          "timestamp": 1725379705
        }
      ]
    },
    {
      "title": "",
      "media_list_data": [
        
      ],
      "string_list_data": [
        {
          "href": "https://www.instagram.com/_elee_naa",
          "value": "_elee_naa",
          "timestamp": 1725308051
        }
      ]
    },
    {
      "title": "",
      "media_list_data": [
        
      ],
      "string_list_data": [
        {
          "href": "https://www.instagram.com/kidkunmusic",
          "value": "kidkunmusic",
          "timestamp": 1723726769
        }
      ]
    },
    {
      "title": "",
      "media_list_data": [
        
      ],
      "string_list_data": [
        {
          "href": "https://www.instagram.com/berndaffleck",
          "value": "berndaffleck",
          "timestamp": 1723726709
        }
      ]
    },
    {
      "title": "",
      "media_list_data": [
        
      ],
      "string_list_data": [
        {
          "href": "https://www.instagram.com/_polygonia_",
          "value": "_polygonia_",
          "timestamp": 1722006920
        }
      ]
    },
    {
      "title": "",
      "media_list_data": [
        
      ],
      "string_list_data": [
        {
          "href": "https://www.instagram.com/scheiffo.mm",
          "value": "scheiffo.mm",
          "timestamp": 1721989039
        }
      ]
    },
    {
      "title": "",
      "media_list_data": [
        
      ],
      "string_list_data": [
        {
          "href": "https://www.instagram.com/ki.do.ri",
          "value": "ki.do.ri",
          "timestamp": 1721989030
        }
      ]
    },
    {
      "title": "",
      "media_list_data": [
        
      ],
      "string_list_data": [
        {
          "href": "https://www.instagram.com/laarryah",
          "value": "laarryah",
          "timestamp": 1718230526
        }
      ]
    },
    {
      "title": "",
      "media_list_data": [
        
      ],
      "string_list_data": [
        {
          "href": "https://www.instagram.com/westcode._",
          "value": "westcode._",
          "timestamp": 1718223035
        }
      ]
    },
    {
      "title": "",
      "media_list_data": [
        
      ],
      "string_list_data": [
        {
          "href": "https://www.instagram.com/dee_n._ah",
          "value": "dee_n._ah",
          "timestamp": 1717447830
        }
      ]
    },
    {
      "title": "",
      "media_list_data": [
        
      ],
      "string_list_data": [
        {
          "href": "https://www.instagram.com/ttoxikaa",
          "value": "ttoxikaa",
          "timestamp": 1716287209
        }
      ]
    },
    {
      "title": "",
      "media_list_data": [
        
      ],
      "string_list_data": [
        {
          "href": "https://www.instagram.com/nazz.ve",
          "value": "nazz.ve",
          "timestamp": 1716278104
        }
      ]
    },
    {
      "title": "",
      "media_list_data": [
        
      ],
      "string_list_data": [
        {
          "href": "https://www.instagram.com/warnung__",
          "value": "warnung__",
          "timestamp": 1716278100
        }
      ]
    },
    {
      "title": "",
      "media_list_data": [
        
      ],
      "string_list_data": [
        {
          "href": "https://www.instagram.com/scoped_ar",
          "value": "scoped_ar",
          "timestamp": 1716278086
        }
      ]
    },
    {
      "title": "",
      "media_list_data": [
        
      ],
      "string_list_data": [
        {
          "href": "https://www.instagram.com/timorinker",
          "value": "timorinker",
          "timestamp": 1716278071
        }
      ]
    },
    {
      "title": "",
      "media_list_data": [
        
      ],
      "string_list_data": [
        {
          "href": "https://www.instagram.com/moritzundfreunde",
          "value": "moritzundfreunde",
          "timestamp": 1711060827
        }
      ]
    },
    {
      "title": "",
      "media_list_data": [
        
      ],
      "string_list_data": [
        {
          "href": "https://www.instagram.com/tinomachauer",
          "value": "tinomachauer",
          "timestamp": 1706624429
        }
      ]
    },
    {
      "title": "",
      "media_list_data": [
        
      ],
      "string_list_data": [
        {
          "href": "https://www.instagram.com/groovesick.dj",
          "value": "groovesick.dj",
          "timestamp": 1706624417
        }
      ]
    },
    {
      "title": "",
      "media_list_data": [
        
      ],
      "string_list_data": [
        {
          "href": "https://www.instagram.com/ako__as",
          "value": "ako__as",
          "timestamp": 1706624415
        }
      ]
    },
    {
      "title": "",
      "media_list_data": [
        
      ],
      "string_list_data": [
        {
          "href": "https://www.instagram.com/gruenfeller",
          "value": "gruenfeller",
          "timestamp": 1706624408
        }
      ]
    },
    {
      "title": "",
      "media_list_data": [
        
      ],
      "string_list_data": [
        {
          "href": "https://www.instagram.com/lohmann_null",
          "value": "lohmann_null",
          "timestamp": 1706624406
        }
      ]
    },
    {
      "title": "",
      "media_list_data": [
        
      ],
      "string_list_data": [
        {
          "href": "https://www.instagram.com/sarah2honigg",
          "value": "sarah2honigg",
          "timestamp": 1706624397
        }
      ]
    },
    {
      "title": "",
      "media_list_data": [
        
      ],
      "string_list_data": [
        {
          "href": "https://www.instagram.com/joelaktas.ve",
          "value": "joelaktas.ve",
          "timestamp": 1706624387
        }
      ]
    },
    {
      "title": "",
      "media_list_data": [
        
      ],
      "string_list_data": [
        {
          "href": "https://www.instagram.com/lenarosegraf",
          "value": "lenarosegraf",
          "timestamp": 1706040359
        }
      ]
    },
    {
      "title": "",
      "media_list_data": [
        
      ],
      "string_list_data": [
        {
          "href": "https://www.instagram.com/vil_hayes",
          "value": "vil_hayes",
          "timestamp": 1705524567
        }
      ]
    },
    {
      "title": "",
      "media_list_data": [
        
      ],
      "string_list_data": [
        {
          "href": "https://www.instagram.com/jonathanriecker",
          "value": "jonathanriecker",
          "timestamp": 1705524219
        }
      ]
    },
    {
      "title": "",
      "media_list_data": [
        
      ],
      "string_list_data": [
        {
          "href": "https://www.instagram.com/leia.bx",
          "value": "leia.bx",
          "timestamp": 1704211224
        }
      ]
    },
    {
      "title": "",
      "media_list_data": [
        
      ],
      "string_list_data": [
        {
          "href": "https://www.instagram.com/davy_______",
          "value": "davy_______",
          "timestamp": 1700638941
        }
      ]
    },
    {
      "title": "",
      "media_list_data": [
        
      ],
      "string_list_data": [
        {
          "href": "https://www.instagram.com/selina_vetzberger",
          "value": "selina_vetzberger",
          "timestamp": 1698484515
        }
      ]
    },
    {
      "title": "",
      "media_list_data": [
        
      ],
      "string_list_data": [
        {
          "href": "https://www.instagram.com/ivanemanuelll",
          "value": "ivanemanuelll",
          "timestamp": 1698484511
        }
      ]
    },
    {
      "title": "",
      "media_list_data": [
        
      ],
      "string_list_data": [
        {
          "href": "https://www.instagram.com/lex_shockwerk",
          "value": "lex_shockwerk",
          "timestamp": 1698484503
        }
      ]
    },
    {
      "title": "",
      "media_list_data": [
        
      ],
      "string_list_data": [
        {
          "href": "https://www.instagram.com/lopileone",
          "value": "lopileone",
          "timestamp": 1693771741
        }
      ]
    },
    {
      "title": "",
      "media_list_data": [
        
      ],
      "string_list_data": [
        {
          "href": "https://www.instagram.com/emily_rth",
          "value": "emily_rth",
          "timestamp": 1693399374
        }
      ]
    },
    {
      "title": "",
      "media_list_data": [
        
      ],
      "string_list_data": [
        {
          "href": "https://www.instagram.com/graffitoj99",
          "value": "graffitoj99",
          "timestamp": 1693392720
        }
      ]
    },
    {
      "title": "",
      "media_list_data": [
        
      ],
      "string_list_data": [
        {
          "href": "https://www.instagram.com/jennyressel",
          "value": "jennyressel",
          "timestamp": 1693228412
        }
      ]
    },
    {
      "title": "",
      "media_list_data": [
        
      ],
      "string_list_data": [
        {
          "href": "https://www.instagram.com/jannik10.02",
          "value": "jannik10.02",
          "timestamp": 1693228391
        }
      ]
    },
    {
      "title": "",
      "media_list_data": [
        
      ],
      "string_list_data": [
        {
          "href": "https://www.instagram.com/morgenstern",
          "value": "morgenstern",
          "timestamp": 1693228345
        }
      ]
    },
    {
      "title": "",
      "media_list_data": [
        
      ],
      "string_list_data": [
        {
          "href": "https://www.instagram.com/phlipper_d",
          "value": "phlipper_d",
          "timestamp": 1693228342
        }
      ]
    },
    {
      "title": "",
      "media_list_data": [
        
      ],
      "string_list_data": [
        {
          "href": "https://www.instagram.com/toobris",
          "value": "toobris",
          "timestamp": 1693228334
        }
      ]
    },
    {
      "title": "",
      "media_list_data": [
        
      ],
      "string_list_data": [
        {
          "href": "https://www.instagram.com/romanze.diff",
          "value": "romanze.diff",
          "timestamp": 1692778038
        }
      ]
    },
    {
      "title": "",
      "media_list_data": [
        
      ],
      "string_list_data": [
        {
          "href": "https://www.instagram.com/capitalized.value",
          "value": "capitalized.value",
          "timestamp": 1692778033
        }
      ]
    },
    {
      "title": "",
      "media_list_data": [
        
      ],
      "string_list_data": [
        {
          "href": "https://www.instagram.com/attics.films",
          "value": "attics.films",
          "timestamp": 1688180554
        }
      ]
    },
    {
      "title": "",
      "media_list_data": [
        
      ],
      "string_list_data": [
        {
          "href": "https://www.instagram.com/andrada.stnx",
          "value": "andrada.stnx",
          "timestamp": 1688180553
        }
      ]
    },
    {
      "title": "",
      "media_list_data": [
        
      ],
      "string_list_data": [
        {
          "href": "https://www.instagram.com/mowrins",
          "value": "mowrins",
          "timestamp": 1688180517
        }
      ]
    },
    {
      "title": "",
      "media_list_data": [
        
      ],
      "string_list_data": [
        {
          "href": "https://www.instagram.com/hei.banana",
          "value": "hei.banana",
          "timestamp": 1688180509
        }
      ]
    },
    {
      "title": "",
      "media_list_data": [
        
      ],
      "string_list_data": [
        {
          "href": "https://www.instagram.com/romy_s_station",
          "value": "romy_s_station",
          "timestamp": 1681808376
        }
      ]
    },
    {
      "title": "",
      "media_list_data": [
        
      ],
      "string_list_data": [
        {
          "href": "https://www.instagram.com/l.i.li",
          "value": "l.i.li",
          "timestamp": 1680734789
        }
      ]
    },
    {
      "title": "",
      "media_list_data": [
        
      ],
      "string_list_data": [
        {
          "href": "https://www.instagram.com/she.vage",
          "value": "she.vage",
          "timestamp": 1680733784
        }
      ]
    },
    {
      "title": "",
      "media_list_data": [
        
      ],
      "string_list_data": [
        {
          "href": "https://www.instagram.com/fukumachi_",
          "value": "fukumachi_",
          "timestamp": 1680733274
        }
      ]
    },
    {
      "title": "",
      "media_list_data": [
        
      ],
      "string_list_data": [
        {
          "href": "https://www.instagram.com/betrugotrad_tatt",
          "value": "betrugotrad_tatt",
          "timestamp": 1679039841
        }
      ]
    },
    {
      "title": "",
      "media_list_data": [
        
      ],
      "string_list_data": [
        {
          "href": "https://www.instagram.com/townes.dj",
          "value": "townes.dj",
          "timestamp": 1679039826
        }
      ]
    },
    {
      "title": "",
      "media_list_data": [
        
      ],
      "string_list_data": [
        {
          "href": "https://www.instagram.com/katinkiminki",
          "value": "katinkiminki",
          "timestamp": 1678866337
        }
      ]
    },
    {
      "title": "",
      "media_list_data": [
        
      ],
      "string_list_data": [
        {
          "href": "https://www.instagram.com/ziskomusic",
          "value": "ziskomusic",
          "timestamp": 1678866286
        }
      ]
    },
    {
      "title": "",
      "media_list_data": [
        
      ],
      "string_list_data": [
        {
          "href": "https://www.instagram.com/lasziv__",
          "value": "lasziv__",
          "timestamp": 1678866261
        }
      ]
    },
    {
      "title": "",
      "media_list_data": [
        
      ],
      "string_list_data": [
        {
          "href": "https://www.instagram.com/mara_.sophie",
          "value": "mara_.sophie",
          "timestamp": 1677359075
        }
      ]
    },
    {
      "title": "",
      "media_list_data": [
        
      ],
      "string_list_data": [
        {
          "href": "https://www.instagram.com/mokarran.dj",
          "value": "mokarran.dj",
          "timestamp": 1677359024
        }
      ]
    },
    {
      "title": "",
      "media_list_data": [
        
      ],
      "string_list_data": [
        {
          "href": "https://www.instagram.com/innsaei.dj",
          "value": "innsaei.dj",
          "timestamp": 1677359016
        }
      ]
    },
    {
      "title": "",
      "media_list_data": [
        
      ],
      "string_list_data": [
        {
          "href": "https://www.instagram.com/paulhauck_",
          "value": "paulhauck_",
          "timestamp": 1677359012
        }
      ]
    },
    {
      "title": "",
      "media_list_data": [
        
      ],
      "string_list_data": [
        {
          "href": "https://www.instagram.com/kai.fson",
          "value": "kai.fson",
          "timestamp": 1676736191
        }
      ]
    },
    {
      "title": "",
      "media_list_data": [
        
      ],
      "string_list_data": [
        {
          "href": "https://www.instagram.com/_xyiz_",
          "value": "_xyiz_",
          "timestamp": 1676736187
        }
      ]
    },
    {
      "title": "",
      "media_list_data": [
        
      ],
      "string_list_data": [
        {
          "href": "https://www.instagram.com/nicolasvoglertechno",
          "value": "nicolasvoglertechno",
          "timestamp": 1676736185
        }
      ]
    },
    {
      "title": "",
      "media_list_data": [
        
      ],
      "string_list_data": [
        {
          "href": "https://www.instagram.com/yanamaste",
          "value": "yanamaste",
          "timestamp": 1676736180
        }
      ]
    },
    {
      "title": "",
      "media_list_data": [
        
      ],
      "string_list_data": [
        {
          "href": "https://www.instagram.com/x.si.ze.x",
          "value": "x.si.ze.x",
          "timestamp": 1676736177
        }
      ]
    },
    {
      "title": "",
      "media_list_data": [
        
      ],
      "string_list_data": [
        {
          "href": "https://www.instagram.com/feelixderhase",
          "value": "feelixderhase",
          "timestamp": 1676736169
        }
      ]
    },
    {
      "title": "",
      "media_list_data": [
        
      ],
      "string_list_data": [
        {
          "href": "https://www.instagram.com/hydenmusic",
          "value": "hydenmusic",
          "timestamp": 1673707835
        }
      ]
    },
    {
      "title": "",
      "media_list_data": [
        
      ],
      "string_list_data": [
        {
          "href": "https://www.instagram.com/__p__a__u__1__",
          "value": "__p__a__u__1__",
          "timestamp": 1673707816
        }
      ]
    },
    {
      "title": "",
      "media_list_data": [
        
      ],
      "string_list_data": [
        {
          "href": "https://www.instagram.com/tbxx_gleis44",
          "value": "tbxx_gleis44",
          "timestamp": 1673707807
        }
      ]
    },
    {
      "title": "",
      "media_list_data": [
        
      ],
      "string_list_data": [
        {
          "href": "https://www.instagram.com/vander_quallen",
          "value": "vander_quallen",
          "timestamp": 1673707805
        }
      ]
    },
    {
      "title": "",
      "media_list_data": [
        
      ],
      "string_list_data": [
        {
          "href": "https://www.instagram.com/hannes_thebruce",
          "value": "hannes_thebruce",
          "timestamp": 1673707804
        }
      ]
    },
    {
      "title": "",
      "media_list_data": [
        
      ],
      "string_list_data": [
        {
          "href": "https://www.instagram.com/redroomsberlin",
          "value": "redroomsberlin",
          "timestamp": 1672500716
        }
      ]
    },
    {
      "title": "",
      "media_list_data": [
        
      ],
      "string_list_data": [
        {
          "href": "https://www.instagram.com/lakher.live",
          "value": "lakher.live",
          "timestamp": 1671137042
        }
      ]
    },
    {
      "title": "",
      "media_list_data": [
        
      ],
      "string_list_data": [
        {
          "href": "https://www.instagram.com/anneke_laurent",
          "value": "anneke_laurent",
          "timestamp": 1671137021
        }
      ]
    },
    {
      "title": "",
      "media_list_data": [
        
      ],
      "string_list_data": [
        {
          "href": "https://www.instagram.com/slomo.uf",
          "value": "slomo.uf",
          "timestamp": 1671137015
        }
      ]
    },
    {
      "title": "",
      "media_list_data": [
        
      ],
      "string_list_data": [
        {
          "href": "https://www.instagram.com/masha.ursyntax",
          "value": "masha.ursyntax",
          "timestamp": 1671136812
        }
      ]
    },
    {
      "title": "",
      "media_list_data": [
        
      ],
      "string_list_data": [
        {
          "href": "https://www.instagram.com/veroschhh",
          "value": "veroschhh",
          "timestamp": 1670946968
        }
      ]
    },
    {
      "title": "",
      "media_list_data": [
        
      ],
      "string_list_data": [
        {
          "href": "https://www.instagram.com/vincent._.paul",
          "value": "vincent._.paul",
          "timestamp": 1670946932
        }
      ]
    },
    {
      "title": "",
      "media_list_data": [
        
      ],
      "string_list_data": [
        {
          "href": "https://www.instagram.com/nati.drb",
          "value": "nati.drb",
          "timestamp": 1670946901
        }
      ]
    },
    {
      "title": "",
      "media_list_data": [
        
      ],
      "string_list_data": [
        {
          "href": "https://www.instagram.com/pinolinoo",
          "value": "pinolinoo",
          "timestamp": 1669814644
        }
      ]
    },
    {
      "title": "",
      "media_list_data": [
        
      ],
      "string_list_data": [
        {
          "href": "https://www.instagram.com/blackmirrorpark",
          "value": "blackmirrorpark",
          "timestamp": 1669814642
        }
      ]
    },
    {
      "title": "",
      "media_list_data": [
        
      ],
      "string_list_data": [
        {
          "href": "https://www.instagram.com/godmustbewoman",
          "value": "godmustbewoman",
          "timestamp": 1669814639
        }
      ]
    },
    {
      "title": "",
      "media_list_data": [
        
      ],
      "string_list_data": [
        {
          "href": "https://www.instagram.com/annemievictoria",
          "value": "annemievictoria",
          "timestamp": 1669219177
        }
      ]
    },
    {
      "title": "",
      "media_list_data": [
        
      ],
      "string_list_data": [
        {
          "href": "https://www.instagram.com/kursiv.de",
          "value": "kursiv.de",
          "timestamp": 1669219139
        }
      ]
    },
    {
      "title": "",
      "media_list_data": [
        
      ],
      "string_list_data": [
        {
          "href": "https://www.instagram.com/ackermannmusic",
          "value": "ackermannmusic",
          "timestamp": 1669219047
        }
      ]
    },
    {
      "title": "",
      "media_list_data": [
        
      ],
      "string_list_data": [
        {
          "href": "https://www.instagram.com/leoncburg",
          "value": "leoncburg",
          "timestamp": 1669215891
        }
      ]
    },
    {
      "title": "",
      "media_list_data": [
        
      ],
      "string_list_data": [
        {
          "href": "https://www.instagram.com/tascamboy",
          "value": "tascamboy",
          "timestamp": 1669215889
        }
      ]
    },
    {
      "title": "",
      "media_list_data": [
        
      ],
      "string_list_data": [
        {
          "href": "https://www.instagram.com/concussion.cnc",
          "value": "concussion.cnc",
          "timestamp": 1669215875
        }
      ]
    },
    {
      "title": "",
      "media_list_data": [
        
      ],
      "string_list_data": [
        {
          "href": "https://www.instagram.com/iglo_music",
          "value": "iglo_music",
          "timestamp": 1669215868
        }
      ]
    },
    {
      "title": "",
      "media_list_data": [
        
      ],
      "string_list_data": [
        {
          "href": "https://www.instagram.com/lyza.music",
          "value": "lyza.music",
          "timestamp": 1669215866
        }
      ]
    },
    {
      "title": "",
      "media_list_data": [
        
      ],
      "string_list_data": [
        {
          "href": "https://www.instagram.com/symbolsaroundu",
          "value": "symbolsaroundu",
          "timestamp": 1669215857
        }
      ]
    },
    {
      "title": "",
      "media_list_data": [
        
      ],
      "string_list_data": [
        {
          "href": "https://www.instagram.com/genexinmotion",
          "value": "genexinmotion",
          "timestamp": 1669215856
        }
      ]
    },
    {
      "title": "",
      "media_list_data": [
        
      ],
      "string_list_data": [
        {
          "href": "https://www.instagram.com/__ikari__",
          "value": "__ikari__",
          "timestamp": 1669215854
        }
      ]
    },
    {
      "title": "",
      "media_list_data": [
        
      ],
      "string_list_data": [
        {
          "href": "https://www.instagram.com/volpearg",
          "value": "volpearg",
          "timestamp": 1669215850
        }
      ]
    },
    {
      "title": "",
      "media_list_data": [
        
      ],
      "string_list_data": [
        {
          "href": "https://www.instagram.com/maloer.records",
          "value": "maloer.records",
          "timestamp": 1669215841
        }
      ]
    },
    {
      "title": "",
      "media_list_data": [
        
      ],
      "string_list_data": [
        {
          "href": "https://www.instagram.com/rill_syntop",
          "value": "rill_syntop",
          "timestamp": 1669034115
        }
      ]
    },
    {
      "title": "",
      "media_list_data": [
        
      ],
      "string_list_data": [
        {
          "href": "https://www.instagram.com/ansmedias",
          "value": "ansmedias",
          "timestamp": 1668498006
        }
      ]
    },
    {
      "title": "",
      "media_list_data": [
        
      ],
      "string_list_data": [
        {
          "href": "https://www.instagram.com/siaelph",
          "value": "siaelph",
          "timestamp": 1668497972
        }
      ]
    },
    {
      "title": "",
      "media_list_data": [
        
      ],
      "string_list_data": [
        {
          "href": "https://www.instagram.com/alex_ko_25",
          "value": "alex_ko_25",
          "timestamp": 1668497955
        }
      ]
    },
    {
      "title": "",
      "media_list_data": [
        
      ],
      "string_list_data": [
        {
          "href": "https://www.instagram.com/laurennagel91",
          "value": "laurennagel91",
          "timestamp": 1668497935
        }
      ]
    },
    {
      "title": "",
      "media_list_data": [
        
      ],
      "string_list_data": [
        {
          "href": "https://www.instagram.com/lxvniv",
          "value": "lxvniv",
          "timestamp": 1668497928
        }
      ]
    },
    {
      "title": "",
      "media_list_data": [
        
      ],
      "string_list_data": [
        {
          "href": "https://www.instagram.com/hanna.eleni",
          "value": "hanna.eleni",
          "timestamp": 1668497856
        }
      ]
    },
    {
      "title": "",
      "media_list_data": [
        
      ],
      "string_list_data": [
        {
          "href": "https://www.instagram.com/marlonas.monte",
          "value": "marlonas.monte",
          "timestamp": 1668497828
        }
      ]
    },
    {
      "title": "",
      "media_list_data": [
        
      ],
      "string_list_data": [
        {
          "href": "https://www.instagram.com/freyam16",
          "value": "freyam16",
          "timestamp": 1668461896
        }
      ]
    },
    {
      "title": "",
      "media_list_data": [
        
      ],
      "string_list_data": [
        {
          "href": "https://www.instagram.com/kathithul",
          "value": "kathithul",
          "timestamp": 1667697274
        }
      ]
    },
    {
      "title": "",
      "media_list_data": [
        
      ],
      "string_list_data": [
        {
          "href": "https://www.instagram.com/romy.schwilk",
          "value": "romy.schwilk",
          "timestamp": 1667696601
        }
      ]
    },
    {
      "title": "",
      "media_list_data": [
        
      ],
      "string_list_data": [
        {
          "href": "https://www.instagram.com/demele033",
          "value": "demele033",
          "timestamp": 1667078941
        }
      ]
    },
    {
      "title": "",
      "media_list_data": [
        
      ],
      "string_list_data": [
        {
          "href": "https://www.instagram.com/wkns.1_",
          "value": "wkns.1_",
          "timestamp": 1667078922
        }
      ]
    },
    {
      "title": "",
      "media_list_data": [
        
      ],
      "string_list_data": [
        {
          "href": "https://www.instagram.com/eliassautter",
          "value": "eliassautter",
          "timestamp": 1667041067
        }
      ]
    },
    {
      "title": "",
      "media_list_data": [
        
      ],
      "string_list_data": [
        {
          "href": "https://www.instagram.com/rou_bou",
          "value": "rou_bou",
          "timestamp": 1667041049
        }
      ]
    },
    {
      "title": "",
      "media_list_data": [
        
      ],
      "string_list_data": [
        {
          "href": "https://www.instagram.com/leoniehenes",
          "value": "leoniehenes",
          "timestamp": 1667041039
        }
      ]
    },
    {
      "title": "",
      "media_list_data": [
        
      ],
      "string_list_data": [
        {
          "href": "https://www.instagram.com/secret.sina",
          "value": "secret.sina",
          "timestamp": 1667041029
        }
      ]
    },
    {
      "title": "",
      "media_list_data": [
        
      ],
      "string_list_data": [
        {
          "href": "https://www.instagram.com/waltmeister_",
          "value": "waltmeister_",
          "timestamp": 1661594450
        }
      ]
    },
    {
      "title": "",
      "media_list_data": [
        
      ],
      "string_list_data": [
        {
          "href": "https://www.instagram.com/nobelcortex",
          "value": "nobelcortex",
          "timestamp": 1661594429
        }
      ]
    },
    {
      "title": "",
      "media_list_data": [
        
      ],
      "string_list_data": [
        {
          "href": "https://www.instagram.com/denoo__j",
          "value": "denoo__j",
          "timestamp": 1661450900
        }
      ]
    },
    {
      "title": "",
      "media_list_data": [
        
      ],
      "string_list_data": [
        {
          "href": "https://www.instagram.com/danielwiich",
          "value": "danielwiich",
          "timestamp": 1660562446
        }
      ]
    },
    {
      "title": "",
      "media_list_data": [
        
      ],
      "string_list_data": [
        {
          "href": "https://www.instagram.com/isajtd",
          "value": "isajtd",
          "timestamp": 1658345025
        }
      ]
    },
    {
      "title": "",
      "media_list_data": [
        
      ],
      "string_list_data": [
        {
          "href": "https://www.instagram.com/sasureeeeh",
          "value": "sasureeeeh",
          "timestamp": 1656762161
        }
      ]
    },
    {
      "title": "",
      "media_list_data": [
        
      ],
      "string_list_data": [
        {
          "href": "https://www.instagram.com/ppinjak",
          "value": "ppinjak",
          "timestamp": 1656761642
        }
      ]
    },
    {
      "title": "",
      "media_list_data": [
        
      ],
      "string_list_data": [
        {
          "href": "https://www.instagram.com/ma_xikuhn",
          "value": "ma_xikuhn",
          "timestamp": 1656761632
        }
      ]
    },
    {
      "title": "",
      "media_list_data": [
        
      ],
      "string_list_data": [
        {
          "href": "https://www.instagram.com/roberto.lages",
          "value": "roberto.lages",
          "timestamp": 1656761627
        }
      ]
    },
    {
      "title": "",
      "media_list_data": [
        
      ],
      "string_list_data": [
        {
          "href": "https://www.instagram.com/jayj_2512",
          "value": "jayj_2512",
          "timestamp": 1655888998
        }
      ]
    },
    {
      "title": "",
      "media_list_data": [
        
      ],
      "string_list_data": [
        {
          "href": "https://www.instagram.com/nanielde",
          "value": "nanielde",
          "timestamp": 1655887476
        }
      ]
    },
    {
      "title": "",
      "media_list_data": [
        
      ],
      "string_list_data": [
        {
          "href": "https://www.instagram.com/simon_nld",
          "value": "simon_nld",
          "timestamp": 1655887451
        }
      ]
    },
    {
      "title": "",
      "media_list_data": [
        
      ],
      "string_list_data": [
        {
          "href": "https://www.instagram.com/kadda.muerte",
          "value": "kadda.muerte",
          "timestamp": 1655887444
        }
      ]
    },
    {
      "title": "",
      "media_list_data": [
        
      ],
      "string_list_data": [
        {
          "href": "https://www.instagram.com/caezar.de",
          "value": "caezar.de",
          "timestamp": 1653499619
        }
      ]
    },
    {
      "title": "",
      "media_list_data": [
        
      ],
      "string_list_data": [
        {
          "href": "https://www.instagram.com/steve.moreve",
          "value": "steve.moreve",
          "timestamp": 1653499611
        }
      ]
    },
    {
      "title": "",
      "media_list_data": [
        
      ],
      "string_list_data": [
        {
          "href": "https://www.instagram.com/cosimareka",
          "value": "cosimareka",
          "timestamp": 1651523561
        }
      ]
    },
    {
      "title": "",
      "media_list_data": [
        
      ],
      "string_list_data": [
        {
          "href": "https://www.instagram.com/philippminel",
          "value": "philippminel",
          "timestamp": 1650870313
        }
      ]
    },
    {
      "title": "",
      "media_list_data": [
        
      ],
      "string_list_data": [
        {
          "href": "https://www.instagram.com/maltefial",
          "value": "maltefial",
          "timestamp": 1650870309
        }
      ]
    },
    {
      "title": "",
      "media_list_data": [
        
      ],
      "string_list_data": [
        {
          "href": "https://www.instagram.com/laura.mlni",
          "value": "laura.mlni",
          "timestamp": 1650133382
        }
      ]
    },
    {
      "title": "",
      "media_list_data": [
        
      ],
      "string_list_data": [
        {
          "href": "https://www.instagram.com/broklyynbaby",
          "value": "broklyynbaby",
          "timestamp": 1650132957
        }
      ]
    },
    {
      "title": "",
      "media_list_data": [
        
      ],
      "string_list_data": [
        {
          "href": "https://www.instagram.com/egotot.schimmer",
          "value": "egotot.schimmer",
          "timestamp": 1650132952
        }
      ]
    },
    {
      "title": "",
      "media_list_data": [
        
      ],
      "string_list_data": [
        {
          "href": "https://www.instagram.com/carlazoewenger",
          "value": "carlazoewenger",
          "timestamp": 1650132921
        }
      ]
    },
    {
      "title": "",
      "media_list_data": [
        
      ],
      "string_list_data": [
        {
          "href": "https://www.instagram.com/habdankmax",
          "value": "habdankmax",
          "timestamp": 1650132919
        }
      ]
    },
    {
      "title": "",
      "media_list_data": [
        
      ],
      "string_list_data": [
        {
          "href": "https://www.instagram.com/iam.tdw",
          "value": "iam.tdw",
          "timestamp": 1650132903
        }
      ]
    },
    {
      "title": "",
      "media_list_data": [
        
      ],
      "string_list_data": [
        {
          "href": "https://www.instagram.com/anna_eschker",
          "value": "anna_eschker",
          "timestamp": 1650132896
        }
      ]
    },
    {
      "title": "",
      "media_list_data": [
        
      ],
      "string_list_data": [
        {
          "href": "https://www.instagram.com/heiko.ju",
          "value": "heiko.ju",
          "timestamp": 1648667914
        }
      ]
    },
    {
      "title": "",
      "media_list_data": [
        
      ],
      "string_list_data": [
        {
          "href": "https://www.instagram.com/jannik_165",
          "value": "jannik_165",
          "timestamp": 1648667909
        }
      ]
    },
    {
      "title": "",
      "media_list_data": [
        
      ],
      "string_list_data": [
        {
          "href": "https://www.instagram.com/lvcyxhssnv",
          "value": "lvcyxhssnv",
          "timestamp": 1648667907
        }
      ]
    },
    {
      "title": "",
      "media_list_data": [
        
      ],
      "string_list_data": [
        {
          "href": "https://www.instagram.com/phil.rosr",
          "value": "phil.rosr",
          "timestamp": 1648667906
        }
      ]
    },
    {
      "title": "",
      "media_list_data": [
        
      ],
      "string_list_data": [
        {
          "href": "https://www.instagram.com/calvin_leander",
          "value": "calvin_leander",
          "timestamp": 1648667902
        }
      ]
    },
    {
      "title": "",
      "media_list_data": [
        
      ],
      "string_list_data": [
        {
          "href": "https://www.instagram.com/kai_petzny",
          "value": "kai_petzny",
          "timestamp": 1648667892
        }
      ]
    },
    {
      "title": "",
      "media_list_data": [
        
      ],
      "string_list_data": [
        {
          "href": "https://www.instagram.com/natihalt_",
          "value": "natihalt_",
          "timestamp": 1648667886
        }
      ]
    },
    {
      "title": "",
      "media_list_data": [
        
      ],
      "string_list_data": [
        {
          "href": "https://www.instagram.com/jannesdaur",
          "value": "jannesdaur",
          "timestamp": 1644834532
        }
      ]
    },
    {
      "title": "",
      "media_list_data": [
        
      ],
      "string_list_data": [
        {
          "href": "https://www.instagram.com/andre.j_",
          "value": "andre.j_",
          "timestamp": 1644834529
        }
      ]
    },
    {
      "title": "",
      "media_list_data": [
        
      ],
      "string_list_data": [
        {
          "href": "https://www.instagram.com/sinabrth",
          "value": "sinabrth",
          "timestamp": 1644829064
        }
      ]
    },
    {
      "title": "",
      "media_list_data": [
        
      ],
      "string_list_data": [
        {
          "href": "https://www.instagram.com/luna.profis",
          "value": "luna.profis",
          "timestamp": 1644825926
        }
      ]
    },
    {
      "title": "",
      "media_list_data": [
        
      ],
      "string_list_data": [
        {
          "href": "https://www.instagram.com/fraufennec",
          "value": "fraufennec",
          "timestamp": 1644825465
        }
      ]
    },
    {
      "title": "",
      "media_list_data": [
        
      ],
      "string_list_data": [
        {
          "href": "https://www.instagram.com/nicoehret99",
          "value": "nicoehret99",
          "timestamp": 1644707536
        }
      ]
    },
    {
      "title": "",
      "media_list_data": [
        
      ],
      "string_list_data": [
        {
          "href": "https://www.instagram.com/juliacarolinemarie",
          "value": "juliacarolinemarie",
          "timestamp": 1642967326
        }
      ]
    },
    {
      "title": "",
      "media_list_data": [
        
      ],
      "string_list_data": [
        {
          "href": "https://www.instagram.com/nusamy_",
          "value": "nusamy_",
          "timestamp": 1639566713
        }
      ]
    },
    {
      "title": "",
      "media_list_data": [
        
      ],
      "string_list_data": [
        {
          "href": "https://www.instagram.com/alisakarpitschka",
          "value": "alisakarpitschka",
          "timestamp": 1639566704
        }
      ]
    },
    {
      "title": "",
      "media_list_data": [
        
      ],
      "string_list_data": [
        {
          "href": "https://www.instagram.com/anaa.yx",
          "value": "anaa.yx",
          "timestamp": 1639566687
        }
      ]
    },
    {
      "title": "",
      "media_list_data": [
        
      ],
      "string_list_data": [
        {
          "href": "https://www.instagram.com/maxhabdank",
          "value": "maxhabdank",
          "timestamp": 1639566680
        }
      ]
    },
    {
      "title": "",
      "media_list_data": [
        
      ],
      "string_list_data": [
        {
          "href": "https://www.instagram.com/streuglitzeraufdeinleben_",
          "value": "streuglitzeraufdeinleben_",
          "timestamp": 1633778793
        }
      ]
    },
    {
      "title": "",
      "media_list_data": [
        
      ],
      "string_list_data": [
        {
          "href": "https://www.instagram.com/jojorottinger",
          "value": "jojorottinger",
          "timestamp": 1633778777
        }
      ]
    },
    {
      "title": "",
      "media_list_data": [
        
      ],
      "string_list_data": [
        {
          "href": "https://www.instagram.com/max.gugenhan",
          "value": "max.gugenhan",
          "timestamp": 1633778751
        }
      ]
    },
    {
      "title": "",
      "media_list_data": [
        
      ],
      "string_list_data": [
        {
          "href": "https://www.instagram.com/noah_134_",
          "value": "noah_134_",
          "timestamp": 1621093748
        }
      ]
    },
    {
      "title": "",
      "media_list_data": [
        
      ],
      "string_list_data": [
        {
          "href": "https://www.instagram.com/juliaankuhn",
          "value": "juliaankuhn",
          "timestamp": 1605357253
        }
      ]
    },
    {
      "title": "",
      "media_list_data": [
        
      ],
      "string_list_data": [
        {
          "href": "https://www.instagram.com/cedric_tx",
          "value": "cedric_tx",
          "timestamp": 1605357236
        }
      ]
    },
    {
      "title": "",
      "media_list_data": [
        
      ],
      "string_list_data": [
        {
          "href": "https://www.instagram.com/mxxmo__",
          "value": "mxxmo__",
          "timestamp": 1605357201
        }
      ]
    },
    {
      "title": "",
      "media_list_data": [
        
      ],
      "string_list_data": [
        {
          "href": "https://www.instagram.com/mxwlkurz",
          "value": "mxwlkurz",
          "timestamp": 1598025202
        }
      ]
    },
    {
      "title": "",
      "media_list_data": [
        
      ],
      "string_list_data": [
        {
          "href": "https://www.instagram.com/hettiofficial",
          "value": "hettiofficial",
          "timestamp": 1598025188
        }
      ]
    },
    {
      "title": "",
      "media_list_data": [
        
      ],
      "string_list_data": [
        {
          "href": "https://www.instagram.com/jonas.gu14",
          "value": "jonas.gu14",
          "timestamp": 1598025165
        }
      ]
    },
    {
      "title": "",
      "media_list_data": [
        
      ],
      "string_list_data": [
        {
          "href": "https://www.instagram.com/rico_ascherl",
          "value": "rico_ascherl",
          "timestamp": 1597705302
        }
      ]
    },
    {
      "title": "",
      "media_list_data": [
        
      ],
      "string_list_data": [
        {
          "href": "https://www.instagram.com/namms0nn",
          "value": "namms0nn",
          "timestamp": 1597705297
        }
      ]
    },
    {
      "title": "",
      "media_list_data": [
        
      ],
      "string_list_data": [
        {
          "href": "https://www.instagram.com/ulischobs",
          "value": "ulischobs",
          "timestamp": 1597705272
        }
      ]
    },
    {
      "title": "",
      "media_list_data": [
        
      ],
      "string_list_data": [
        {
          "href": "https://www.instagram.com/alina.zimmnn",
          "value": "alina.zimmnn",
          "timestamp": 1597705269
        }
      ]
    },
    {
      "title": "",
      "media_list_data": [
        
      ],
      "string_list_data": [
        {
          "href": "https://www.instagram.com/niclasschweizer",
          "value": "niclasschweizer",
          "timestamp": 1597705268
        }
      ]
    }
  ]
}